autoapply/__init__.py
autoapply/autoapply.py
autoapply/crypt.py
autoapply/download.py
autoapply/util.py
autoapply-0.3.2.data/scripts/autoapply
autoapply-0.3.2.data/scripts/autoapply-server
autoapply-0.3.2.dist-info/DESCRIPTION.rst
autoapply-0.3.2.dist-info/METADATA
autoapply-0.3.2.dist-info/RECORD
autoapply-0.3.2.dist-info/WHEEL
autoapply-0.3.2.dist-info/metadata.json
autoapply-0.3.2.dist-info/top_level.txt
