Metadata-Version: 2.0
Name: autoapply
Version: 0.3.2
Summary: Automatically apply changes from a remote URL to the Kubernetes cluster
Home-page: https://github.com/pascalgn/autoapply
Author: Pascal
Author-email: UNKNOWN
License: ISC
Platform: UNKNOWN
Requires-Dist: PyYAML (==3.12)
Requires-Dist: cryptography (==2.1.2)
